LICENSE
README.md
setup.py
src/depixelizer/__init__.py
src/depixelizer/cmd.py
src/depixelizer.egg-info/PKG-INFO
src/depixelizer.egg-info/SOURCES.txt
src/depixelizer.egg-info/dependency_links.txt
src/depixelizer.egg-info/entry_points.txt
src/depixelizer.egg-info/top_level.txt
src/depixelizer/depixelize/__init__.py
src/depixelizer/depixelize/depixelize.py
src/depixelizer/depixelize/heuristic.py
src/depixelizer/depixelize/pixel_data.py
src/depixelizer/geometry/__init__.py
src/depixelizer/geometry/bspline.py
src/depixelizer/geometry/path.py
src/depixelizer/geometry/point.py
src/depixelizer/geometry/shape.py
src/depixelizer/geometry/smoothen.py
src/depixelizer/io/__init__.py
src/depixelizer/io/input.py
src/depixelizer/io/output.py