Metadata-Version: 2.1
Name: depixelizer
Version: 0.0.2
Summary: An implementation of the paper Depixelizing Pixel Art by Kopf and Lischinski.
Home-page: https://github.com/vvanirudh/Pixel-Art
Author: Anirudh Vemula, Vamsidhar Yeddu
Author-email: vvanirudh@gmail.com, vamsidhar666@gmail.com
License: UNKNOWN
Project-URL: Bug Tracker, https://github.com/vvanirudh/Pixel-Art/issues
Platform: UNKNOWN
Classifier: Programming Language :: Python :: 3
Requires-Python: >=3.6
License-File: LICENSE
